crypto_currency_price/__init__.py
crypto_currency_price/cli.py
crypto_currency_price/crypto_currency_price.py
crypto_currency_price/version.py
crypto_currency_price/commands/__init__.py
crypto_currency_price/commands/cfg.py
crypto_currency_price/commands/default.py
crypto_currency_price-0.2.1.dist-info/entry_points.txt
crypto_currency_price-0.2.1.dist-info/LICENSE
crypto_currency_price-0.2.1.dist-info/WHEEL
crypto_currency_price-0.2.1.dist-info/METADATA
crypto_currency_price-0.2.1.dist-info/RECORD
